{"chrome://browser/content/browser.xhtml":{"main-window":{"screenX":"45","screenY":"29","width":"1530","height":"2650","sizemode":"maximized"},"sidebar-box":{"sidebarcommand":"viewHistorySidebar","style":"order: 1; width: 271px;"},"sidebar-title":{"value":"History"}},"chrome://browser/content/places/places.xhtml":{"placesContentTags":{"ordinal":"3"},"placesContentUrl":{"ordinal":"5"},"placesContentDate":{"ordinal":"7"},"placesContentVisitCount":{"ordinal":"9"},"placesContentDateAdded":{"ordinal":"11"},"placesContentLastModified":{"ordinal":"13"},"places":{"screenX":"0","screenY":"0","width":"938","height":"651","sizemode":"maximized"},"place:7oeDNC3ogcC3GuvdQk3h1g==":{"open":"true"}},"chrome://browser/content/places/historySidebar.xhtml":{"place:VbETgkP7Ppu2lcLuNVVbSw==":{"open":"true"},"place:C3F6ySRiJ4xQjOsbYgMyow==":{"open":"true"},"place:CvSnWVuu6OAyRGT52TDjbA==":{"open":"true"},"place:It6X62icMMz4RzVcGTJhUw==":{"open":"true"},"place:0bnLxTmrLzKFlGuNWbB9zg==":{"open":"true"}},"chrome://browser/content/pageinfo/pageInfo.xhtml":{"main-window":{"screenX":"4251","screenY":"596","width":"728","height":"550","sizemode":"normal"}},"chrome://mozapps/content/downloads/unknownContentType.xhtml":{"unknownContentTypeWindow":{"screenX":"0","screenY":"0"}}}